{
  "Name": "Wacom CTE-430",
  "Specifications": {
    "Digitizer": {
      "Width": 127.6,
      "Height": 92.8,
      "MaxX": 10208.0,
      "MaxY": 7424.0
    },
    "Pen": {
      "MaxPressure": 511,
      "Buttons": {
        "ButtonCount": 2
      }
    },
    "AuxiliaryButtons": null,
    "MouseButtons": null,
    "Touch": null
  },
  "DigitizerIdentifiers": [
    {
      "VendorID": 1386,
      "ProductID": 19,
      "InputReportLength": 8,
      "OutputReportLength": null,
      "ReportParser": "OpenTabletDriver.Vendors.Wacom.IntuosLegacy.IntuosLegacyReportParser",
      "FeatureInitReport": [
        "AgI="
      ],
      "OutputInitReport": null,
      "DeviceStrings": {},
      "InitializationStrings": []
    },
    {
      "VendorID": 1386,
      "ProductID": 19,
      "InputReportLength": 9,
      "OutputReportLength": null,
      "ReportParser": "OpenTabletDriver.Vendors.Wacom.Intuos.WacomDriverIntuosReportParser",
      "FeatureInitReport": [
        "AgI="
      ],
      "OutputInitReport": null,
      "DeviceStrings": {},
      "InitializationStrings": []
    }
  ],
  "AuxilaryDeviceIdentifiers": [],
  "Attributes": {}
}