{
  "Name": "Huion H430P",
  "DigitizerIdentifiers": [
    {
      "Width": 121.92,
      "Height": 76.2,
      "MaxX": 24384.0,
      "MaxY": 15240.0,
      "MaxPressure": 4095,
      "ActiveReportID": {
        "Start": 64,
        "StartInclusive": true,
        "End": null,
        "EndInclusive": false
      },
      "VendorID": 9580,
      "ProductID": 109,
      "InputReportLength": 12,
      "OutputReportLength": null,
      "ReportParser": "OpenTabletDriver.Tablet.TabletReportParser",
      "FeatureInitReport": null,
      "OutputInitReport": null,
      "DeviceStrings": {
        "201": "HUION_T176_\\d{6}$"
      },
      "InitializationStrings": [
        200
      ]
    },
    {
      "Width": 121.92,
      "Height": 76.2,
      "MaxX": 24384.0,
      "MaxY": 15240.0,
      "MaxPressure": 4095,
      "ActiveReportID": {
        "Start": 64,
        "StartInclusive": true,
        "End": null,
        "EndInclusive": false
      },
      "VendorID": 9580,
      "ProductID": 110,
      "InputReportLength": 12,
      "OutputReportLength": null,
      "ReportParser": "OpenTabletDriver.Tablet.TabletReportParser",
      "FeatureInitReport": null,
      "OutputInitReport": null,
      "DeviceStrings": {
        "201": "HUION_T176_\\d{6}$"
      },
      "InitializationStrings": [
        200
      ]
    }
  ],
  "AuxilaryDeviceIdentifiers": [],
  "Attributes": {
    "libinputoverride": "1"
  }
}