{
  "Name": "Huion New 1060 Plus",
  "DigitizerIdentifier": {
    "VendorID": 9580,
    "ProductID": 109,
    "InputReportLength": 12,
    "OutputReportLength": 0,
    "ReportParser": null,
    "FeatureInitReport": null,
    "OutputInitReport": null
  },
  "AlternateDigitizerIdentifier": {
    "VendorID": 0,
    "ProductID": 0,
    "InputReportLength": 0,
    "OutputReportLength": 0,
    "ReportParser": null,
    "FeatureInitReport": null,
    "OutputInitReport": null
  },
  "AuxilaryDeviceIdentifier": {
    "VendorID": 0,
    "ProductID": 0,
    "InputReportLength": 0,
    "OutputReportLength": 0,
    "ReportParser": null,
    "FeatureInitReport": null,
    "OutputInitReport": null
  },
  "Width": 254.0,
  "Height": 158.75,
  "MaxX": 50800.0,
  "MaxY": 31750.0,
  "MaxPressure": 8191,
  "ActiveReportID": {
    "Start": 128,
    "StartInclusive": false,
    "End": 96,
    "EndInclusive": false
  },
  "Attributes": {},
  "DeviceStrings": {
    "1": "HUION_T174"
  },
  "InitializationStrings": [
    0,
    0
  ]
}