{
  "Name": "Wacom PTH-851",
  "Specifications": {
    "Digitizer": {
      "Width": 325.12,
      "Height": 203.2,
      "MaxX": 65024.0,
      "MaxY": 40640.0
    },
    "Pen": {
      "MaxPressure": 2047,
      "Buttons": {
        "ButtonCount": 2
      }
    },
    "AuxiliaryButtons": {
      "ButtonCount": 8
    },
    "MouseButtons": null,
    "Touch": null
  },
  "DigitizerIdentifiers": [
    {
      "VendorID": 1386,
      "ProductID": 791,
      "InputReportLength": 10,
      "OutputReportLength": null,
      "ReportParser": "OpenTabletDriver.Configurations.Parsers.Wacom.IntuosV1.IntuosV1ReportParser",
      "FeatureInitReport": [
        "AgI="
      ],
      "OutputInitReport": null,
      "DeviceStrings": {},
      "InitializationStrings": []
    },
    {
      "VendorID": 1386,
      "ProductID": 791,
      "InputReportLength": 11,
      "OutputReportLength": null,
      "ReportParser": "OpenTabletDriver.Configurations.Parsers.Wacom.IntuosV1.WacomDriverIntuosV1ReportParser",
      "FeatureInitReport": [
        "AgI="
      ],
      "OutputInitReport": null,
      "DeviceStrings": {},
      "InitializationStrings": []
    }
  ],
  "AuxilaryDeviceIdentifiers": [
    {
      "VendorID": 1386,
      "ProductID": 791,
      "InputReportLength": 64,
      "OutputReportLength": null,
      "ReportParser": "OpenTabletDriver.Configurations.Parsers.Wacom.Wacom64bAuxReportParser",
      "FeatureInitReport": null,
      "OutputInitReport": null,
      "DeviceStrings": {},
      "InitializationStrings": []
    }
  ],
  "Attributes": {}
}