<?xml version="1.0"?>
<Tablet xmlns:xsi="http://www.w3.org/2001/XMLSchema-instance" xmlns:xsd="http://www.w3.org/2001/XMLSchema" xmlns="TabletDriverLib">
  <Name>Wacom CTL-6100</Name>
  <VendorID>1386</VendorID>
  <ProductID>888</ProductID>
  <InputReportLength>192</InputReportLength>
  <CustomInputReportLength>0</CustomInputReportLength>
  <Width>216</Width>
  <Height>135</Height>
  <MaxX>21600</MaxX>
  <MaxY>13500</MaxY>
  <MaxPressure>4095</MaxPressure>
  <MinimumRange>32</MinimumRange>
  <AuxReportLength>0</AuxReportLength>
</Tablet>